adafruit_nunchuk.py
adafruit_circuitpython_nunchuk-1.1.16.dist-info/licenses/LICENSE
adafruit_circuitpython_nunchuk-1.1.16.dist-info/METADATA
adafruit_circuitpython_nunchuk-1.1.16.dist-info/WHEEL
adafruit_circuitpython_nunchuk-1.1.16.dist-info/top_level.txt
adafruit_circuitpython_nunchuk-1.1.16.dist-info/RECORD
