Metadata-Version: 2.4
Name: adafruit-circuitpython-nunchuk
Version: 1.1.16
Summary: CircuitPython library for Nintendo Nunchuk controller
Author-email: Adafruit Industries <circuitpython@adafruit.com>
License: MIT
Project-URL: Homepage, https://github.com/adafruit/Adafruit_CircuitPython_Nunchuk.git
Keywords: adafruit,blinka,circuitpython,micropython,nunchuk,nunchuck,nintendo,controller
Classifier: Intended Audience :: Developers
Classifier: Topic :: Software Development :: Libraries
Classifier: Topic :: Software Development :: Embedded Systems
Classifier: Topic :: System :: Hardware
Classifier: License :: OSI Approved :: MIT License
Classifier: Programming Language :: Python :: 3
License-File: LICENSE
Requires-Dist: Adafruit-Blinka
Requires-Dist: adafruit-circuitpython-busdevice
Provides-Extra: optional
Dynamic: license-file
